{
  "generatedAt": "2026-06-10T13:51:56.702Z",
  "handle": "GulsabiKids",
  "shorts": [
    {
      "id": "hl9EzB1Tgxs",
      "name": "What Is a Comet? | Ice, Dust, Rock and a Space Tail | Gulsabi Kids",
      "seconds": 33
    },
    {
      "id": "r0JSnW7c9HU",
      "name": "Why Should We Have Discipline? | Good Habits for Kids | Gulsabi Kids Songs #curiouskids #butwhy",
      "seconds": 28
    },
    {
      "id": "GBBlDSnU6kU",
      "name": "Why Do Chameleons Change Color? 🦎 | Fun Science for Kids | Gulsabi #curiouskids  #scienceforkids",
      "seconds": 31
    },
    {
      "id": "BJY1cNgL8gw",
      "name": "Why Does the Moon Have Craters? | Moon Facts for Kids | Gulsabi #curiouskids  #kidssong #gulsabi",
      "seconds": 31
    },
    {
      "id": "g6nq5VgRCQQ",
      "name": "Why Do Octopuses Spray Ink? | Fun Ocean Facts for Kids | Gulsabi #curiouskids",
      "seconds": 34
    },
    {
      "id": "ZokkR58KTzc",
      "name": "Why Do Volcanoes Erupt? 🌋 | Fun Volcano Song for Kids | Gulsabi #nurseryrhymes #butwhy",
      "seconds": 38
    },
    {
      "id": "BiqMmCSMv64",
      "name": "Why Do Shrimps Molt Their Shells? | Shrimp Molting Explained for Kids | Gulsabi #curiouskids",
      "seconds": 39
    },
    {
      "id": "g3RzCOq2U5M",
      "name": "Why Do Leaves Have Different Colors? 🍁 | Fun Science for Kids | Gulsabi #curiouskids",
      "seconds": 29
    },
    {
      "id": "M6qEElIzZc8",
      "name": "Where Does Wind Come From? 🌬️ | Fun Science for Kids | Ask WHY with Gulsabi #curiouskids  #butwhy",
      "seconds": 31
    },
    {
      "id": "s8-7rJGOkUw",
      "name": "How Are Clothes Made? 👕🧵 | Kids Learn Clothing Making | Ask HOW with Gulsabi #curiouskids #askhow",
      "seconds": 29
    },
    {
      "id": "jrugxbgxCeg",
      "name": "How Is Glass Made? 🔥 | Glass Factory for Kids | Ask HOW with Gulsabi! #curiouskids #scienceforkids",
      "seconds": 31
    },
    {
      "id": "MLb4ak__C3c",
      "name": "Why Does Fire Feel Hot? 🔥 | Fun Science for Kids | Ask WHY with Gulsabi!#curiosity #curiouskids",
      "seconds": 31
    },
    {
      "id": "7lNx94AuARc",
      "name": "Why Do We Fold Clothes? 👕🧺 | Fun Kids Learning Song | Ask WHY with Gulsabi! #curiosity  #kidssong",
      "seconds": 26
    },
    {
      "id": "1YUqLFd-xJQ",
      "name": "What Is a Telescope? | Space for Kids | Ask WHY with Gulsabi! #curiosity  #nurseryrhymes #butwhy",
      "seconds": 30
    },
    {
      "id": "R-N36CEPYd4",
      "name": "Why Do Whales Spray Water? | Fun Whale Facts for Kids | Ask WHY with Gulsabi! #oceanfacts",
      "seconds": 31
    },
    {
      "id": "dhOhUIPcFus",
      "name": "Why Is Mars Red? | Mars for Kids | Ask WHY with Gulsabi! #curiouskids  #nurseryrhymes",
      "seconds": 44
    },
    {
      "id": "H8l0OABGZqA",
      "name": "Why Do Crabs Walk Sideways? 🦀 | Fun Crab Facts for Kids | Ask WHY with Gulsabi! #scienceforkids",
      "seconds": 31
    },
    {
      "id": "ClrgU193dXM",
      "name": "Why Do We Wear Helmets? | Kids Safety Song | Ask WHY with Gulsabi #curiosity #scienceforkids",
      "seconds": 34
    },
    {
      "id": "hTymICKl26U",
      "name": "Why Do Lizards Drop Their Tails? | Kids Science Song 🦎 | Ask WHY with Gulsabi! #butwhy  #cartoon",
      "seconds": 35
    },
    {
      "id": "hGTU883Iucc",
      "name": "Where Do Rivers Flow? | River Flow Explained for Kids | Ask WHY with Gulsabi #nurseryrhymes #butwhy",
      "seconds": 36
    },
    {
      "id": "hu03v8BUs78",
      "name": "Why Does Our Heart Beat? | Heart Pumping Blood Explained for Kids | Ask WHY with Gulsabi #butwhy",
      "seconds": 25
    },
    {
      "id": "IxZksXYRQIk",
      "name": "Why Do I Feel Hot Under the Sun? | Kids Science Song | Ask WHY with Gulsabi  #butwhy #curiosity",
      "seconds": 31
    },
    {
      "id": "xR6p1S57Wic",
      "name": "Why Do We Blink? | Fun Science for Kids | Eye Protection Explained | Ask WHY with Gulsabi #curiosity",
      "seconds": 34
    },
    {
      "id": "0t7W9d7eFlg",
      "name": "Why Do We Cut Our Nails? | Kids Hygiene Song | Ask WHY with Gulsabi #rhymes #butwhy #curiosity",
      "seconds": 37
    },
    {
      "id": "WIk_5dRpte4",
      "name": "Why Do Waves Move? | Kids Science Explained | Wind Makes Waves | Gulsabi  #kids#butwhy #curiosity",
      "seconds": 40
    },
    {
      "id": "QV9dQTEq488",
      "name": "Why Do We Dream? | Fun Science for Kids | Ask WHY with Gulsabi  #kidssong #butwhy #curiosity",
      "seconds": 36
    },
    {
      "id": "T37kQ_FVf8c",
      "name": "Why Do Fish Swim in Groups? | Ask WHY with Gulsabi 🐟  #gulsabi #butwhy #curiosity  #kidssong",
      "seconds": 37
    },
    {
      "id": "IR6ouhV3VvQ",
      "name": "How Does an AC Make Air Cold? | Simple Science for Kids | Gulsabi  #kidssong #butwhy #curiosity",
      "seconds": 44
    },
    {
      "id": "fa9gW760mU4",
      "name": "Why Do We Chew Before We Swallow? | Fun Science Song for Kids  #kidssong #butwhy #gulsabi #curiosity",
      "seconds": 32
    },
    {
      "id": "yfhE5aBryrE",
      "name": "Why Do Zebras Have Black and White Stripes? | Ask WHY with Gulsabi  #kids#butwhy #cartoon #curiosity",
      "seconds": 31
    },
    {
      "id": "UnNZQcdQtNo",
      "name": "Why Is the Ocean Salty? 🌊 | Ask WHY with Gulsabi #gulsabi #curiosity #kidsscience #askwhy",
      "seconds": 40
    },
    {
      "id": "xrH-36b0bPw",
      "name": "Why Do We Get Lice in Hair? | Kids Science Song | Ask WHY with Gulsabi #LICE #curiosity #butwhy",
      "seconds": 37
    },
    {
      "id": "HBN1cfDJtnI",
      "name": "Big Leaves vs Tiny Leaves | Why Are Leaves Different Sizes? | Ask WHY with Gulsabi  #curiosity",
      "seconds": 41
    },
    {
      "id": "hmkpHtTf7Ww",
      "name": "Why Do Flies Find Food So Fast? | Ask WHY with Gulsabi #kidssong #butwhy #cartoon #curiosity",
      "seconds": 38
    },
    {
      "id": "2HJ2bmkg9fY",
      "name": "Why Do We Drink Water? | Fun Kids Science Song 💧 #gulsabi #butwhy #cartoon #curiosity #kidssong",
      "seconds": 44
    },
    {
      "id": "JoLHIpK1Ye8",
      "name": "Why Are Seashells White? Simple Science for Kids | Gulsabi | #kidssong #butwhy #cartoon #curiosity",
      "seconds": 37
    },
    {
      "id": "3YdRYXCf7d0",
      "name": "Why Is Snow Cold? | Fun Science for Kids | Ask WHY with Gulsabi  #butwhy #kidssong #curiosity",
      "seconds": 39
    },
    {
      "id": "ljO1BGxrhPk",
      "name": "Why Do We Eat Healthy Food? 🍎⚡ Energy vs Sugar Crash | Ask WHY with Gulsabi  #gulsabi #butwhy",
      "seconds": 40
    },
    {
      "id": "ZUZXAvLtnDM",
      "name": "Why Are Night-Blooming Flowers Mostly White? | Ask WHY with Gulsabi  #butwhy #kidssong #curiosity",
      "seconds": 39
    },
    {
      "id": "BWYCGTNP5aY",
      "name": "How Do Seeds Grow Into Trees | Kids Learning with Gulsabi  #gulsabi #kidssong #buthow #curiosity",
      "seconds": 43
    },
    {
      "id": "DCqhGU50Tjw",
      "name": "How Does a Caterpillar Become a Butterfly? | Real Metamorphosis for Kids #gulsabi #kidssong #butwhy",
      "seconds": 46
    },
    {
      "id": "rCuYs94Fl9U",
      "name": "Why Do Mirrors Show Your Face? | Light Reflection Explained for Kids  #gulsabi #butwhy #kids",
      "seconds": 34
    },
    {
      "id": "O1-HfUif64w",
      "name": "Why Do Things Fall Down? | Gravity Explained for Kids |  #gulsabi #butwhy #kidssong #curiosity",
      "seconds": 31
    },
    {
      "id": "39vN6RdRbX0",
      "name": "Why Doesn’t Artemis II Land on the Moon?  #gulsabi #artemis2  #butwhy #kidssong #curiosity #butwhy",
      "seconds": 31
    },
    {
      "id": "Yh_qNHcA0Wk",
      "name": "Why do we hiccup?  #gulsabi #butwhy  #curiosity #preschoollearning #askwhy #nurseryrhymes",
      "seconds": 40
    },
    {
      "id": "JUFkVtTiY_A",
      "name": "Why Did Dinosaurs Disappear? #gulsabi #butwhy #kidssong #curiosity #animation #askwhy #preschool",
      "seconds": 46
    },
    {
      "id": "RDJmW78ov0Y",
      "name": "Why Do Owls Stay Awake at Night? 🦉 #gulsabi #kidssong #butwhy #curiosity #owlfacts #birds",
      "seconds": 40
    },
    {
      "id": "G0Y-z5afzlM",
      "name": "Why do we hear echoes? #kidslearning #gulsabi #butwhy #curiosity #kids #preschool #scienceforkids",
      "seconds": 30
    },
    {
      "id": "nui_NyTDYHE",
      "name": "Why Do We Say Sorry? #kidslearning #gulsabi #butwhy #askwhy #kids#emotionalintelligence   #curiosity",
      "seconds": 34
    },
    {
      "id": "TtrPQk7FnEc",
      "name": "Why Does Soda Fizz When You Open It? #kidslearning #gulsabi #butwhy#kidsscience  #askwhy #curiosity",
      "seconds": 32
    },
    {
      "id": "CnVWARbbCdg",
      "name": "Why Are Leaves Green? 🌿 #kidslearning #gulsabi #butwhy #curiosity #askwhy #kids #scienceforkids",
      "seconds": 26
    },
    {
      "id": "-lK57iIDkTw",
      "name": "Why cover cough, tell me why? #kidslearning #gulsabi #butwhy #curiosity #hygieneforkids #hygiene",
      "seconds": 32
    },
    {
      "id": "Y8tmZt2Iw_M",
      "name": "Why Do We Have Hair?  #kidslearning #gulsabi #butwhy #curiosity #curiouskids #askwhy #kids",
      "seconds": 42
    },
    {
      "id": "D8mJ6qjGVgE",
      "name": "Tick-Tock Clock Explained | Why Do Clocks Tick? | #kidslearning #butwhy #gulsabi #curiosity #askwhy",
      "seconds": 34
    },
    {
      "id": "okmde5Melag",
      "name": "Why do we sleep? #kidslearning #gulsabi #butwhy #curiosity #askwhy #curiouskids #kids #kidsscience",
      "seconds": 35
    },
    {
      "id": "eKDaNs3aZp8",
      "name": "Why Does Rain Fall? #kidslearning #gulsabi #butwhy #curiosity #askwhy   #kids #curiouskids",
      "seconds": 36
    },
    {
      "id": "IGEZ5HPjEcs",
      "name": "Why do fish live in water? #kidslearning #butwhy #gulsabi #curiosity #askwhy #kids #kidsscience",
      "seconds": 35
    },
    {
      "id": "l_R_HsgjwuU",
      "name": "Why do fireflies glow at night? #kidslearning #gulsabi #butwhy #curiosity #askwhy #firefly",
      "seconds": 46
    },
    {
      "id": "NAUii46y-A0",
      "name": "Why Do Flowers Smell Nice? #kidslearning #gulsabi #butwhy #curiosity #askwhy #kids #flowers",
      "seconds": 39
    },
    {
      "id": "1WQU7FRdDck",
      "name": "Why Throw Trash? Clean World Song for Kids #kidslearning #butwhy #curiosity #askwhy #kids #gulsabi",
      "seconds": 36
    },
    {
      "id": "09CqK7-wTJw",
      "name": "Why Should I Share myToys?  #kidslearning #gulsabi #butwhy #curiosity#sharing  #curiouskids #askwhy",
      "seconds": 32
    },
    {
      "id": "BYJXOz3tdq4",
      "name": "Why Wear a Seatbelt? #kidslearning#seatbeltsafety  #butwhy #askwhy #curiouskids #curiosity #kids",
      "seconds": 32
    },
    {
      "id": "YXTkT3B8P4M",
      "name": "Why Should We Keep Our Toys Clean? #kidslearning #gulsabi #butwhy #curiosity #hygiene #toys",
      "seconds": 26
    },
    {
      "id": "Rw4YTe5N1O0",
      "name": "Why Should We Eat Vegetables Every Day? #kidslearning #butwhy  #askwhy #curiosity #healthyfood",
      "seconds": 42
    },
    {
      "id": "5jk59KBloUY",
      "name": "Why Do We Go to School? #kidslearning #butwhy #curiosity #curiouskids #kids #askwhy #school",
      "seconds": 36
    },
    {
      "id": "sg1NHw7loWk",
      "name": "Why Do We Wash Hands? Kids Hygiene Song #kidslearning #butwhy #curiosity #hygiene  #kids",
      "seconds": 46
    },
    {
      "id": "RlKeRQX_8sI",
      "name": "Why Is Grass Wet in the Morning? #kidslearning #butwhy #gulsabi #curiouskid #kids #askwhy #curiosity",
      "seconds": 46
    },
    {
      "id": "oqVx1OJyUl4",
      "name": "Why Is the Sky Blue? #kidslearning #butwhy #curiouskids #kids #curiosity #askwhy #preschoollearning",
      "seconds": 35
    },
    {
      "id": "K_ILOMutb9g",
      "name": "Why Do Butterflies Have Colorful Wings?w8 #kidslearning #gulsabi #butwhy  #curiouskids #kids",
      "seconds": 35
    },
    {
      "id": "vL-U2vOmUH0",
      "name": "Why does my shadow follow me everywhere? #kidslearning #butwhy #curiosity",
      "seconds": 41
    },
    {
      "id": "wnJfT90KztE",
      "name": "Why Do Spiders Make Webs? |",
      "seconds": 41
    },
    {
      "id": "os-VHoUw1Iw",
      "name": "Why Do Ants March in a Line? #kidslearning #kids #butwhy #curiosity #animation #cartoon #askwhy",
      "seconds": 43
    },
    {
      "id": "HrCKL8h8Rx8",
      "name": "Why Does the Moon Change Shape? #kidslearning #animation #kids #curiosity #butwhy #children #cartoon",
      "seconds": 44
    },
    {
      "id": "x9ktisKRFoE",
      "name": "Why Do We Brush Our Teeth? | Ask WHY with Gulsabi #kidslearning #kids #animation #curiosity #butwhy",
      "seconds": 40
    },
    {
      "id": "BL6mh4F9DH4",
      "name": "Why Do Rainbows Appear? 🌈 #kidslearning #animation #kids #curiosity #butwhy #askwhy #children",
      "seconds": 29
    },
    {
      "id": "391eNjnfnD8",
      "name": "Why do birds fly? 🐦 #animation #kidslearning #kids #askwhy #cartoon #butwhy #curiosity #curiouskids",
      "seconds": 32
    },
    {
      "id": "aovcG7-BRUY",
      "name": "Meet Gulsabi, the little superhero for curious kids. WHY.#Gulsabi #CuriousKids #AskWhy",
      "seconds": 32
    }
  ],
  "videos": [
    {
      "id": "5v6WWlDS-js",
      "name": "Why? Why? Why? | 15 Fun Science & Curiosity Songs for Kids | Gulsabi Kids",
      "seconds": 600
    },
    {
      "id": "p8hc_JH-MyU",
      "name": "Gulsabi Introduction 1",
      "seconds": 65
    }
  ]
}
